./.gitignore
./.pythonrc.py
./CHANGELOG.md
./LICENSE
./Library_Details.md
./Multiple conventional commits with semantic versioning.md
./README.md
./main.py
./mkdocs.yml
./py.typed
./pyproject.toml
./sign.py
./uv.lock
./.github/workflows/release.yml
./.idea/.gitignore
./.idea/MBot.iml
./.idea/misc.xml
./.idea/modules.xml
./.idea/vcs.xml
./.idea/webResources.xml
./.idea/workspace.xml
./.idea/inspectionProfiles/Project_Default.xml
./.idea/inspectionProfiles/profiles_settings.xml
./.scripts/release.sh
./docs/api.md
./docs/index.md
./docs/logging.md
./docs/registry.md
./docs/img/favicon.ico
./docs/img/logo.png
./docs/style/mkdocstrings-bak.css
./docs/style/mkdocstrings.css
./docs/style/style.css
./examples/README.md
./examples/API/README.md
./examples/API/inventory.py
./examples/API/raid.py
./examples/Registry/README.md
./examples/Registry/fetch_player.py
./examples/Registry/register_player.py
./mhanndalorian_bot/__init__.py
./mhanndalorian_bot/api.py
./mhanndalorian_bot/attrs.py
./mhanndalorian_bot/base.py
./mhanndalorian_bot/config.py
./mhanndalorian_bot/registry.py
./mhanndalorian_bot/utils.py
./mhanndalorian_bot/version.py
./tests/test_api.py
./tests/test_base.py
./tests/test_registry.py
mhanndalorian_bot-0.10.0.dist-info/METADATA
mhanndalorian_bot-0.10.0.dist-info/WHEEL
mhanndalorian_bot-0.10.0.dist-info/licenses/LICENSE
mhanndalorian_bot-0.10.0.dist-info/RECORD
