Metadata-Version: 2.4
Name: mhanndalorian-bot
Version: 0.10.0
Summary: Python 3 interface library for the Mhanndalorianbot authenticated endpoints API
Author-email: Mar Trepodi <martrepodi@gmail.com>
License-File: LICENSE
Classifier: Development Status :: 3 - Alpha
Classifier: Intended Audience :: Developers
Classifier: License :: OSI Approved :: MIT License
Classifier: Operating System :: OS Independent
Classifier: Programming Language :: Python :: 3
Classifier: Topic :: Software Development
Classifier: Topic :: Software Development :: Libraries
Classifier: Topic :: Software Development :: Libraries :: Python Modules
Classifier: Topic :: Utilities
Requires-Python: >=3.10
Requires-Dist: hatchling>=1.27.0
Requires-Dist: httpx
Requires-Dist: pytest>=8.4.2
Requires-Dist: sentinels
